LICENSE.txt
mtw_tk.py
setup.cfg
setup.py
mtw_tk.egg-info/PKG-INFO
mtw_tk.egg-info/SOURCES.txt
mtw_tk.egg-info/dependency_links.txt
mtw_tk.egg-info/top_level.txt